{"Points":[{"X":465,"Y":328},{"X":465,"Y":331},{"X":462,"Y":338},{"X":458,"Y":348},{"X":452,"Y":360},{"X":444,"Y":371},{"X":434,"Y":386},{"X":422,"Y":401},{"X":411,"Y":409},{"X":392,"Y":418},{"X":370,"Y":427},{"X":343,"Y":433},{"X":314,"Y":438},{"X":288,"Y":443},{"X":263,"Y":443},{"X":241,"Y":443},{"X":219,"Y":443},{"X":202,"Y":437},{"X":178,"Y":422},{"X":161,"Y":408},{"X":144,"Y":397},{"X":133,"Y":385},{"X":127,"Y":375},{"X":124,"Y":367},{"X":123,"Y":358},{"X":123,"Y":351},{"X":123,"Y":345},{"X":123,"Y":339},{"X":125,"Y":334},{"X":127,"Y":332},{"X":131,"Y":330},{"X":136,"Y":328},{"X":144,"Y":328},{"X":152,"Y":328},{"X":179,"Y":329},{"X":205,"Y":340},{"X":241,"Y":358},{"X":278,"Y":377},{"X":313,"Y":399},{"X":336,"Y":416},{"X":355,"Y":431},{"X":373,"Y":446},{"X":386,"Y":459},{"X":399,"Y":467},{"X":411,"Y":477},{"X":418,"Y":481},{"X":424,"Y":484},{"X":427,"Y":486},{"X":428,"Y":486},{"X":429,"Y":486},{"X":429,"Y":486},{"X":430,"Y":486}],"Name":"alpha"}