{"Points":[{"X":433,"Y":360},{"X":427,"Y":375},{"X":417,"Y":395},{"X":391,"Y":428},{"X":364,"Y":457},{"X":343,"Y":469},{"X":329,"Y":474},{"X":322,"Y":476},{"X":314,"Y":476},{"X":306,"Y":474},{"X":298,"Y":470},{"X":288,"Y":464},{"X":280,"Y":457},{"X":271,"Y":452},{"X":267,"Y":446},{"X":264,"Y":440},{"X":262,"Y":429},{"X":262,"Y":421},{"X":262,"Y":413},{"X":263,"Y":408},{"X":268,"Y":405},{"X":275,"Y":405},{"X":281,"Y":405},{"X":298,"Y":405},{"X":318,"Y":415},{"X":331,"Y":422},{"X":343,"Y":430},{"X":351,"Y":438},{"X":361,"Y":446},{"X":373,"Y":454},{"X":384,"Y":459},{"X":393,"Y":463},{"X":402,"Y":467},{"X":405,"Y":468},{"X":406,"Y":469},{"X":406,"Y":469},{"X":408,"Y":469}],"Name":"alpha"}