{"Points":[{"X":317,"Y":349},{"X":318,"Y":349},{"X":318,"Y":349},{"X":320,"Y":350},{"X":321,"Y":353},{"X":323,"Y":359},{"X":326,"Y":365},{"X":327,"Y":372},{"X":329,"Y":379},{"X":332,"Y":386},{"X":335,"Y":394},{"X":338,"Y":402},{"X":342,"Y":410},{"X":346,"Y":425},{"X":349,"Y":433},{"X":354,"Y":441},{"X":355,"Y":448},{"X":357,"Y":454},{"X":360,"Y":459},{"X":362,"Y":462},{"X":363,"Y":464},{"X":363,"Y":466},{"X":365,"Y":468},{"X":365,"Y":470},{"X":365,"Y":471},{"X":365,"Y":472},{"X":366,"Y":472},{"X":367,"Y":473},{"X":367,"Y":473},{"X":368,"Y":474},{"X":368,"Y":474},{"X":371,"Y":474},{"X":374,"Y":469},{"X":377,"Y":459},{"X":384,"Y":448},{"X":387,"Y":440},{"X":393,"Y":430},{"X":399,"Y":420},{"X":406,"Y":410},{"X":413,"Y":399},{"X":421,"Y":388},{"X":427,"Y":379},{"X":432,"Y":371},{"X":435,"Y":367},{"X":435,"Y":365},{"X":438,"Y":363},{"X":439,"Y":361},{"X":440,"Y":361}],"Name":"vshape"}